pandas_etl_pipeline/__init__.py
pandas_etl_pipeline/pipeline.py
pandas_etl_pipeline-0.1.0.dist-info/LICENSE
pandas_etl_pipeline-0.1.0.dist-info/METADATA
pandas_etl_pipeline-0.1.0.dist-info/WHEEL
pandas_etl_pipeline-0.1.0.dist-info/top_level.txt
pandas_etl_pipeline-0.1.0.dist-info/RECORD
