Metadata-Version: 2.1
Name: pandas-etl-pipeline
Version: 0.1.0
Summary: Package for creating ETL pipelines with Pandas DataFrames.
Home-page: https://github.com/rob-dalton/pandas-etl-pipeline
Author: Rob Dalton
License: UNKNOWN
Platform: UNKNOWN
Classifier: Programming Language :: Python :: 3
Classifier: License :: OSI Approved :: MIT License
Classifier: Operating System :: OS Independent
Requires-Python: >=3.8
